[
    {
        "ReportId": 99329,
        "ReportName": "BaseFile 99329 20250912124625",
        "FileName": "BaseFile_99329_20250912124625.json",
        "CompanyLogoFilePath": "database/companyLogos/sample-logo.png",
        "Currency": "US Dollar",
        "CreatedOn": "2025-09-12T12:46:25.717554"
    },
    {
        "ReportId": 41393,
        "ReportName": "BaseFile 41393 20250912124825",
        "FileName": "BaseFile_41393_20250912124825.json",
        "CompanyLogoFilePath": "database/companyLogos/sample-logo.png",
        "Currency": "US Dollar",
        "CreatedOn": "2025-09-12T12:48:26.161136"
    },
    {
        "ReportId": 72791,
        "ReportName": "BaseFile 72791 20250912125739",
        "FileName": "BaseFile_72791_20250912125739.json",
        "CompanyLogoFilePath": "database/companyLogos/logo_72791_20250912130245.png",
        "Currency": "US Dollar",
        "CreatedOn": "2025-09-12T12:57:39.381922"
    },
    {
        "ReportId": 58079,
        "ReportName": "BaseFile 58079 20250915110650",
        "FileName": "BaseFile_58079_20250915110650.json",
        "CompanyLogoFilePath": "database/companyLogos/sample-logo.png",
        "Currency": "US Dollar",
        "CreatedOn": "2025-09-15T11:06:50.796935"
    },
    {
        "ReportId": 43915,
        "ReportName": "BaseFile 43915 20250915111117",
        "FileName": "BaseFile_43915_20250915111117.json",
        "CompanyLogoFilePath": "database/companyLogos/sample-logo.png",
        "Currency": "US Dollar",
        "CreatedOn": "2025-09-15T11:11:17.435120"
    },
    {
        "ReportId": 32414,
        "ReportName": "BaseFile 32414 20250915115903",
        "FileName": "BaseFile_32414_20250915115903.json",
        "CompanyLogoFilePath": "database/companyLogos/sample-logo.png",
        "Currency": "US Dollar",
        "CreatedOn": "2025-09-15T11:59:04.165847"
    },
    {
        "ReportId": 16755,
        "ReportName": "BaseFile 16755 20250915120002",
        "FileName": "BaseFile_16755_20250915120002.json",
        "CompanyLogoFilePath": "database/companyLogos/logo_16755_20250915182607.png",
        "Currency": "US Dollar",
        "CreatedOn": "2025-09-15T12:00:02.776878"
    },
    {
        "ReportId": 76581,
        "ReportName": "BaseFile 76581 20250915163609",
        "FileName": "BaseFile_76581_20250915163609.json",
        "CompanyLogoFilePath": "database/companyLogos/sample-logo.png",
        "Currency": "US Dollar",
        "CreatedOn": "2025-09-15T16:36:09.408194"
    },
    {
        "ReportId": 56282,
        "ReportName": "BaseFile 56282 20250918105507",
        "FileName": "BaseFile_56282_20250918105507.json",
        "CompanyLogoFilePath": "database/companyLogos/sample-logo.png",
        "Currency": "US Dollar",
        "CreatedOn": "2025-09-18T10:55:07.769398"
    }
]